diffx_python-0.6.1.dist-info/METADATA
diffx_python-0.6.1.dist-info/WHEEL
diffx_python-0.6.1.dist-info/licenses/LICENSE
diffx_python/__init__.py
diffx_python/diffx_python.cpython-311-darwin.so
diffx_python-0.6.1.dist-info/RECORD
