Metadata-Version: 2.4
Name: diffx-python
Version: 0.6.1
Classifier: Development Status :: 4 - Beta
Classifier: Intended Audience :: Developers
Classifier: License :: OSI Approved :: MIT License
Classifier: Programming Language :: Python :: 3
Classifier: Programming Language :: Python :: 3.8
Classifier: Programming Language :: Python :: 3.9
Classifier: Programming Language :: Python :: 3.10
Classifier: Programming Language :: Python :: 3.11
Classifier: Programming Language :: Python :: 3.12
Classifier: Programming Language :: Python :: 3.13
Classifier: Programming Language :: Rust
Classifier: Topic :: Software Development :: Libraries :: Python Modules
Classifier: Topic :: Text Processing
Classifier: Topic :: Utilities
Requires-Dist: pytest>=6.0 ; extra == 'dev'
Requires-Dist: pytest-cov ; extra == 'dev'
Requires-Dist: black ; extra == 'dev'
Requires-Dist: isort ; extra == 'dev'
Requires-Dist: mypy ; extra == 'dev'
Requires-Dist: ruff ; extra == 'dev'
Provides-Extra: dev
License-File: LICENSE
Summary: Python bindings for diffx - semantic diffing of JSON, YAML, TOML, XML, INI, and CSV files. Powered by Rust for blazing fast performance.
Keywords: diff,json,yaml,toml,xml,ini,csv,structured,semantic,comparison,devops,ci-cd,automation,data-analysis,pyo3,rust
Author: kako-jun
License-Expression: MIT
Requires-Python: >=3.8
Project-URL: Homepage, https://github.com/kako-jun/diffx-python
Project-URL: Repository, https://github.com/kako-jun/diffx-python
Project-URL: Issues, https://github.com/kako-jun/diffx-python/issues
Project-URL: Documentation, https://github.com/kako-jun/diffx-python#readme
